aihive_tools/duckduckgo/__init__.py
aihive_tools/duckduckgo/tools.py
aihive_tools_duckduckgo-0.0.5.dist-info/METADATA
aihive_tools_duckduckgo-0.0.5.dist-info/WHEEL
aihive_tools_duckduckgo-0.0.5.dist-info/top_level.txt
aihive_tools_duckduckgo-0.0.5.dist-info/RECORD
